ngroktoduckdns/__init__.py
ngroktoduckdns/ngroktoduckdns.py
NgroktoDuckDNS-0.0.6.dist-info/METADATA
NgroktoDuckDNS-0.0.6.dist-info/WHEEL
NgroktoDuckDNS-0.0.6.dist-info/entry_points.txt
NgroktoDuckDNS-0.0.6.dist-info/top_level.txt
NgroktoDuckDNS-0.0.6.dist-info/RECORD
