Metadata-Version: 2.1
Name: NgroktoDuckDNS
Version: 0.0.6
Summary: Expose local services to the web through duckdns with ngrok.
Home-page: UNKNOWN
Author: GrandMoff100
Author-email: nlarsen23.student@gmail.com
License: UNKNOWN
Platform: UNKNOWN
Requires-Dist: click
Requires-Dist: pyngrok
Requires-Dist: requests
